CIC/__init__.py
CIC/cem.py
CIC/cemSEIS.py
CIC/circlePacking.py
CIC/defensiveIS.py
CIC/mh.py
cicriterion-1.0.dist-info/METADATA
cicriterion-1.0.dist-info/WHEEL
cicriterion-1.0.dist-info/top_level.txt
cicriterion-1.0.dist-info/RECORD
