Metadata-Version: 2.1
Name: cicriterion
Version: 1.0
Summary: Implementation of the cross-entropy information criterion and related algorithms.
Home-page: https://github.com/nick-terry/CIC
Author: Nick Terry, Youngjun Choe
Author-email: pnterry@uw.edu
License: UNKNOWN
Project-URL: Bug Tracker, https://github.com/nick-terry/CIC/issues
Platform: UNKNOWN
Classifier: Programming Language :: Python :: 3
Classifier: License :: OSI Approved :: GNU General Public License v3 (GPLv3)
Classifier: Operating System :: OS Independent
Requires-Python: >=3.6
Requires-Dist: cvxpy (>=1.1.12)
Requires-Dist: dccp (>=1.0.3)
Requires-Dist: matplotlib (>=3.3.1)
Requires-Dist: numpy (>=1.19.2)
Requires-Dist: pandas (>=1.1.2)
Requires-Dist: scipy (>=1.6.3)
